fullGSapi/api/__init__.py
fullGSapi/api/assignment_grader.py
fullGSapi/api/assignments.py
fullGSapi/api/autograder.py
fullGSapi/api/cdata.py
fullGSapi/api/client.py
fullGSapi/api/gs_api_client.py
fullGSapi/api/login_tokens.py
fullGSapi/api/online_assignment.py
fullGSapi/api/threadpool.py
fullGSapi/api/utils.py
fullGSapi/cli/__init__.py
fullGSapi/cli/__main__.py
fullGSapi/cli/build.py
fullGSapi/cli/download_commands.py
fullGSapi/cli/login.py
fullGSapi/cli/submit.py
fullGSapi/cli/utils.py
fullGSapi-1.3.11.dist-info/LICENSE
fullGSapi-1.3.11.dist-info/METADATA
fullGSapi-1.3.11.dist-info/WHEEL
fullGSapi-1.3.11.dist-info/entry_points.txt
fullGSapi-1.3.11.dist-info/top_level.txt
fullGSapi-1.3.11.dist-info/RECORD
