Metadata-Version: 2.1
Name: fullGSapi
Version: 1.3.11
Summary: UNKNOWN
Home-page: UNKNOWN
Author: ThaumicMekanism
Author-email: thaumicmekanism@gmail.com
License: MIT
Platform: UNKNOWN
Requires-Python: >=3.6
Requires-Dist: cryptography
Requires-Dist: beautifulsoup4
Requires-Dist: py-mini-racer
Requires-Dist: requests
Requires-Dist: pyyaml
Requires-Dist: python-dateutil
Provides-Extra: cli
Requires-Dist: click ; extra == 'cli'
Requires-Dist: tqdm ; extra == 'cli'
Requires-Dist: pytz ; extra == 'cli'
